MANIFEST.in
README.md
requirements.txt
setup.py
grologs/__init__.py
grologs/grologs.py
grologs.egg-info/PKG-INFO
grologs.egg-info/SOURCES.txt
grologs.egg-info/dependency_links.txt
grologs.egg-info/not-zip-safe
grologs.egg-info/requires.txt
grologs.egg-info/top_level.txt